LICENSE
MANIFEST.in
README
setup.py
version.py
rask_cronpoke/__init__.py
rask_cronpoke.egg-info/PKG-INFO
rask_cronpoke.egg-info/SOURCES.txt
rask_cronpoke.egg-info/dependency_links.txt
rask_cronpoke.egg-info/requires.txt
rask_cronpoke.egg-info/top_level.txt