Metadata-Version: 1.0
Name: rask-cronpoke
Version: 0.1.2
Summary: Rask Cronpoke Connector
Home-page: https://gitlab.com/vikingmakt/rask_cronpoke
Author: Felipe Paolozze
Author-email: felipe@vikingmakt.com.br
License: https://gitlab.com/vikingmakt/rask_cronpoke/raw/master/LICENSE
Platform: UNKNOWN
